dollar/__init__.py
dollar-0.1.0.dist-info/LICENSE
dollar-0.1.0.dist-info/WHEEL
dollar-0.1.0.dist-info/METADATA
dollar-0.1.0.dist-info/RECORD
